{"mentions":[{"id":"3253260762","alert_id":461518,"title":"SPRUG: SPB Ruby User Group - Community - Google+","description":"Got even more excited about Ruby Object Mapper after listening to RubyRogues   Ep. 123 with @solnic. #twt http:\/\/rubyrogues.com\/123-rr-rom-with-piotr-solnica\/.","url":"https:\/\/plus.google.com\/communities\/117927540789820622012","unique_id":"https:\/\/plus.google.com\/communities\/117927540789820622012","published_at":"2013-10-18T21:57:08.40799100+00:00","created_at":"2013-10-18T21:57:09.0+00:00","updated_at":"2013-10-18T21:57:09.0+00:00","favorite":false,"trashed":false,"trashed_set_by_user":false,"read":true,"tone":1,"tone_score":0.99686,"relevance_score":0,"source_type":"web","source_name":"google.com","source_url":"https:\/\/plus.google.com","language_code":"en","tasks":[],"logs":[],"children":[],"important":false,"offsets":{"title":[11,11,4,4],"description":[28,28,4,4,33,33,6,6,40,40,6,6,66,66,4,4,113,113,4,4,135,135,3,3],"url":[],"source_name":[],"source_url":[]},"permissions":{"favorite":true,"trash":true,"create_task":false}},{"id":"3259883082","alert_id":461518,"title":"127 RR Erik Michaels-Ober - Ruby Rogues","description":"ERIK: Yeah, so I was actually listening to a Ruby Rogues episode a few weeks ago with Piotr Solnica and he mentioned a bunch of gems that came out of the ROM project, the Ruby Object Mapper. And I tried just using them. I looked them up ...","url":"http:\/\/rubyrogues.com\/127-rr-erik-michaels-ober\/","unique_id":"http:\/\/rubyrogues.com\/127-rr-erik-michaels-ober\/","published_at":"2013-10-16T13:00:42.84034500+00:00","created_at":"2013-10-19T11:55:40.0+00:00","updated_at":"2013-10-22T04:33:43.0+00:00","favorite":true,"trashed":false,"trashed_set_by_user":false,"read":true,"tone":0,"tone_score":0.13167,"relevance_score":0,"source_type":"blogs","source_name":"Charles Max Wood","source_url":"http:\/\/rubyrogues.com\/","language_code":"en","tasks":[],"logs":[{"id":"18854292","type":"favorited","author":{"id":"209170_64b8a6q53wkks8k0k80c04o8osskc8w0scs8gsk4gco8kg8csw","name":"Michael Ries","email":"michael@riesd.com","language_code":"en","registration_client":"web","inviter_id":"209170_44yhohlf","created_at":"2013-10-06T22:09:48.0+00:00","updated_at":"2013-10-22T04:28:34.0+00:00","avatar_url":"https:\/\/web.mention.net\/avatars\/e5b3508d3d0178000d994ad8e4b50e2f-b36057eb7794d441.jpg"},"created_at":"2013-10-22T04:33:43.0+00:00"}],"children":[],"important":false,"offsets":{"title":[28,28,4,4],"description":[45,45,4,4,154,154,3,3,171,171,4,4,176,176,6,6,183,183,6,6],"url":[7,7,4,4],"source_name":[],"source_url":[7,7,4,4]},"permissions":{"favorite":true,"trash":true,"create_task":false}},{"id":"3199497112","alert_id":461518,"title":"#rom-rb on 2013-10-14 \u2014 irc logs at whitequark.org","description":"2013-06-04 15:26 solnic changed the topic of #rom-rb to: Ruby Object Mapper |   Mailing List: https:\/\/groups.google.com\/forum\/?fromgroups#!forum\/rom-rb | Logs:  \u00a0...","url":"http:\/\/irclog.whitequark.org\/rom-rb\/","unique_id":"http:\/\/irclog.whitequark.org\/rom-rb\/","published_at":"2013-10-15T06:02:29.54474800+00:00","created_at":"2013-10-15T06:02:30.0+00:00","updated_at":"2013-10-15T06:02:31.0+00:00","favorite":false,"trashed":false,"trashed_set_by_user":false,"read":true,"tone":1,"tone_score":0.89703,"relevance_score":0,"source_type":"web","source_name":"whitequark.org","source_url":"http:\/\/irclog.whitequark.org","language_code":"en","tasks":[],"logs":[],"children":[],"important":false,"offsets":{"title":[1,1,3,3],"description":[46,46,3,3,57,57,4,4,62,62,6,6,69,69,6,6,145,145,3,3],"url":[29,29,3,3],"source_name":[],"source_url":[]},"permissions":{"favorite":true,"trash":true,"create_task":false}},{"id":"3199497192","alert_id":461518,"title":"rom-rb (Ruby Object Mapper) \u00b7 GitHub","description":"Ruby Object Mapper rom-rb. http:\/\/rom-rb.org; Joined on Jun 01, 2013 ... Ruby   Object Mapper - vagrant vm setup with environment prepared for ROM\u00a0...","url":"https:\/\/github.com\/rom-rb","unique_id":"https:\/\/github.com\/rom-rb","published_at":"2013-10-15T06:02:29.54465700+00:00","created_at":"2013-10-15T06:02:31.0+00:00","updated_at":"2013-10-22T04:33:35.0+00:00","favorite":true,"trashed":false,"trashed_set_by_user":false,"read":true,"tone":0,"tone_score":0.23322,"relevance_score":0,"source_type":"web","source_name":"github.com","source_url":"https:\/\/github.com","language_code":"en","tasks":[],"logs":[{"id":"18854282","type":"favorited","author":{"id":"209170_64b8a6q53wkks8k0k80c04o8osskc8w0scs8gsk4gco8kg8csw","name":"Michael Ries","email":"michael@riesd.com","language_code":"en","registration_client":"web","inviter_id":"209170_44yhohlf","created_at":"2013-10-06T22:09:48.0+00:00","updated_at":"2013-10-22T04:28:34.0+00:00","avatar_url":"https:\/\/web.mention.net\/avatars\/e5b3508d3d0178000d994ad8e4b50e2f-b36057eb7794d441.jpg"},"created_at":"2013-10-22T04:33:35.0+00:00"}],"children":[],"important":false,"offsets":{"title":[0,0,3,3,8,8,4,4,13,13,6,6,20,20,6,6],"description":[0,0,4,4,5,5,6,6,12,12,6,6,19,19,3,3,34,34,3,3,73,73,4,4,80,80,6,6,87,87,6,6,143,143,3,3],"url":[19,19,3,3],"source_name":[],"source_url":[]},"permissions":{"favorite":true,"trash":true,"create_task":false}},{"id":"3170907802","alert_id":461518,"title":"Joining Relations with Ruby Object Mapper - JJask.com","description":"Does anyone know of a good example of doing reads and write with joined data   from Ruby Object Mapper? -- EDIT to include more details --. My ROM schema\u00a0...","url":"http:\/\/www.jjask.com\/417722\/joining-relations-with-ruby-object-mapper","unique_id":"http:\/\/www.jjask.com\/417722\/joining-relations-with-ruby-object-mapper","published_at":"2013-10-13T03:13:01.23992800+00:00","created_at":"2013-10-13T03:13:01.0+00:00","updated_at":"2013-10-13T03:13:01.0+00:00","favorite":false,"trashed":false,"trashed_set_by_user":false,"read":true,"tone":1,"tone_score":0.99723,"relevance_score":0,"source_type":"web","source_name":"jjask.com","source_url":"http:\/\/www.jjask.com","language_code":"en","tasks":[],"logs":[],"children":[],"important":false,"offsets":{"title":[23,23,4,4,28,28,6,6,35,35,6,6],"description":[84,84,4,4,89,89,6,6,96,96,6,6,143,143,3,3],"url":[51,51,4,4,56,56,6,6,63,63,6,6],"source_name":[],"source_url":[]},"permissions":{"favorite":true,"trash":true,"create_task":false}},{"id":"3133336282","alert_id":461518,"title":"Wikipedia:Requested articles\/Applied arts and sciences\/Computer ...","description":"\"Potion is an object- and mixin-oriented (traits) language. ... Macronix is a manufacturer of rom memory. www.macronix.com ..... Geoffrey Grosenbach - founder of PeepCode Screencasts and Ruby on Rails podcast; [125]]; George .... Wilhelm Oddo Ml  \u2026","url":"http:\/\/en.wikipedia.org\/wiki\/Wikipedia:Requested_articles\/Applied_arts_and_sciences\/Computer_science,_computing,_and_Internet","unique_id":"http:\/\/en.wikipedia.org\/wiki\/Wikipedia:Requested_articles\/Applied_arts_and_sciences\/Computer_science,_computing,_and_Internet","published_at":"2013-10-10T12:45:25.18839700+00:00","created_at":"2013-10-10T12:45:25.0+00:00","updated_at":"2013-10-10T12:45:25.0+00:00","favorite":false,"trashed":false,"trashed_set_by_user":false,"read":true,"tone":0,"tone_score":1,"relevance_score":0,"source_type":"web","source_name":"wikipedia.org","source_url":"http:\/\/en.wikipedia.org","language_code":"en","tasks":[],"logs":[],"children":[],"important":false,"offsets":{"title":[],"description":[14,14,6,6,94,94,3,3,187,187,4,4],"url":[],"source_name":[],"source_url":[]},"permissions":{"favorite":true,"trash":true,"create_task":false}},{"id":"3133336402","alert_id":461518,"title":"Ruby Rogues","description":"Confident Ruby by Avdi Grimm! ... 123 RR ROM with Piotr Solnica ... Rails Ramp Up) Discussion 01:24 \u2013 Piotr Solnica Introduction Ruby Object Mapper 06:08\u00a0...","url":"http:\/\/rubyrogues.com\/","unique_id":"http:\/\/rubyrogues.com\/","published_at":"2013-10-10T12:45:25.18828500+00:00","created_at":"2013-10-10T12:45:25.0+00:00","updated_at":"2013-10-10T12:45:26.0+00:00","favorite":false,"trashed":false,"trashed_set_by_user":false,"read":true,"tone":1,"tone_score":0.97604,"relevance_score":0,"source_type":"web","source_name":"rubyrogues.com","source_url":"http:\/\/rubyrogues.com","language_code":"en","tasks":[],"logs":[],"children":[],"important":false,"offsets":{"title":[0,0,4,4],"description":[10,10,4,4,41,41,3,3,129,129,4,4,134,134,6,6,141,141,6,6],"url":[7,7,4,4],"source_name":[0,0,4,4],"source_url":[7,7,4,4]},"permissions":{"favorite":true,"trash":true,"create_task":false}},{"id":"3109778052","alert_id":461518,"title":"Buddenbaum.de - Heise","description":"Maker Faire Rom: Heimspiel f\u00fcr Arduino ... Ruby-Implementierung Rubinius in der Gegenwart angekommen .... Landsat Enhanced Thematic Mapper Plus (ETM +) data are used to generate finer ...... Bayesian object-based estimation of LAI and chlorophyll from \u2026","url":"http:\/\/buddenbaum.de\/index.php?inhalt=heise.ct&layout=layout16.ph&submenu=8","unique_id":"http:\/\/buddenbaum.de\/index.php?inhalt=heise.ct&layout=layout16.ph&submenu=8","published_at":"2013-10-08T20:35:28.46928600+00:00","created_at":"2013-10-08T20:35:28.0+00:00","updated_at":"2013-10-08T20:35:28.0+00:00","favorite":false,"trashed":false,"trashed_set_by_user":false,"read":true,"tone":0,"tone_score":1,"relevance_score":0,"source_type":"web","source_name":"buddenbaum.de","source_url":"http:\/\/buddenbaum.de","language_code":"en","tasks":[],"logs":[],"children":[],"important":false,"offsets":{"title":[],"description":[12,12,3,3,43,43,4,4,132,132,6,6,200,200,6,6],"url":[],"source_name":[],"source_url":[]},"permissions":{"favorite":true,"trash":true,"create_task":false}},{"id":"3098889462","alert_id":461518,"title":"Joining Relations","description":"Michael Ries ... rom-rb Hi - I opened a question on stackoverflow about how to join relations in ruby object mapper.","url":"http:\/\/groups.google.com\/g\/4f27c98a\/t\/b2ea5a96ce5377a5\/d\/a06559b71ac8626b","unique_id":"http:\/\/groups.google.com\/g\/4f27c98a\/t\/b2ea5a96ce5377a5\/d\/a06559b71ac8626b","published_at":"2013-10-08T03:56:36.91432700+00:00","created_at":"2013-10-08T03:56:36.0+00:00","updated_at":"2013-10-08T03:56:36.0+00:00","favorite":false,"trashed":false,"trashed_set_by_user":false,"read":true,"tone":1,"tone_score":0.97152,"relevance_score":0,"source_type":"forums","source_name":"google.com","source_url":"http:\/\/groups.google.com","language_code":"en","tasks":[],"logs":[],"children":[],"important":false,"offsets":{"title":[],"description":[17,17,3,3,97,97,4,4,102,102,6,6,109,109,6,6],"url":[],"source_name":[],"source_url":[]},"permissions":{"favorite":true,"trash":true,"create_task":false}}],"_links":{"pull":{"href":"\/api\/accounts\/209170_64b8a6q53wkks8k0k80c04o8osskc8w0scs8gsk4gco8kg8csw\/alerts\/461518\/mentions?limit=20&since_id=3285351912","params":{"limit":20,"since_id":"3285351912"}}},"recently_reenabled":false}
